LICENSE
MANIFEST.in
README.md
pyproject.toml
setup.cfg
setup.py
ph4_walkingpad/__init__.py
ph4_walkingpad/analysis.py
ph4_walkingpad/cal.py
ph4_walkingpad/cmd_helper.py
ph4_walkingpad/errors.py
ph4_walkingpad/main.py
ph4_walkingpad/pad.py
ph4_walkingpad/profile.py
ph4_walkingpad/reader.py
ph4_walkingpad/upload.py
ph4_walkingpad/utils.py
ph4_walkingpad.egg-info/PKG-INFO
ph4_walkingpad.egg-info/SOURCES.txt
ph4_walkingpad.egg-info/dependency_links.txt
ph4_walkingpad.egg-info/entry_points.txt
ph4_walkingpad.egg-info/requires.txt
ph4_walkingpad.egg-info/top_level.txt