Metadata-Version: 2.1
Name: ph4-walkingpad
Version: 1.0.0
Summary: Walkingpad A1 controller via Bluetooth LE
Home-page: https://github.com/ph4r05/ph4-walkingpad
Author: Dusan Klinec
Author-email: dusan.klinec@gmail.com
License: MIT
Classifier: Development Status :: 3 - Alpha
Classifier: Intended Audience :: Developers
Classifier: Programming Language :: Python
Classifier: Programming Language :: Python :: 2
Classifier: Programming Language :: Python :: 2.6
Classifier: Programming Language :: Python :: 2.7
Classifier: Programming Language :: Python :: 3
Classifier: Programming Language :: Python :: 3.3
Classifier: Programming Language :: Python :: 3.4
Classifier: Programming Language :: Python :: 3.5
License-File: LICENSE
Requires-Dist: setuptools>=1.0
Requires-Dist: six
Requires-Dist: future
Requires-Dist: asyncio
Requires-Dist: coloredlogs
Requires-Dist: bleak>=0.14.1
Requires-Dist: ph4-acmd2==0.0.5
Requires-Dist: blessed
Requires-Dist: requests
Requires-Dist: aioconsole==0.3.1
Provides-Extra: dev
Requires-Dist: pep8; extra == "dev"
Requires-Dist: pypandoc; extra == "dev"
Requires-Dist: pre-commit; extra == "dev"
Requires-Dist: types-requests; extra == "dev"
Requires-Dist: mypy; extra == "dev"
Requires-Dist: pytest; extra == "dev"
Provides-Extra: docs
Requires-Dist: Sphinx>=1.0; extra == "docs"
Requires-Dist: sphinx_rtd_theme; extra == "docs"
Requires-Dist: sphinxcontrib-programoutput; extra == "docs"
